<?xml version="1.0" encoding="utf-8"?>
<!DOCTYPE hibernate-mapping PUBLIC "-//Hibernate/Hibernate Mapping DTD 3.0//EN"
"http://www.hibernate.org/dtd/hibernate-mapping-3.0.dtd">
<!-- 
    Mapping file autogenerated by MyEclipse Persistence Tools
-->
<hibernate-mapping>
    <class name="hiber.Competiteur" table="competiteur" catalog="gestion">
        <id name="idCompetiteur" type="java.lang.Integer">
            <column name="id_Competiteur" />
            <generator class="assigned" />
        </id>
        <property name="numeroLigue" type="java.lang.String">
            <column name="numero_Ligue" length="9" not-null="true" />
        </property>
        <set name="joues" inverse="true">
            <key>
                <column name="id_Competiteur" not-null="true" />
            </key>
            <one-to-many class="hiber.Joue" />
        </set>
        <set name="obtients" inverse="true">
            <key>
                <column name="id_Competiteur" not-null="true" />
            </key>
            <one-to-many class="hiber.Obtient" />
        </set>
        <set name="estAffilies" inverse="true">
            <key>
                <column name="id_Competiteur" not-null="true" unique="true" />
            </key>
            <one-to-many class="hiber.EstAffilie" />
        </set>
    </class>
</hibernate-mapping>
